lab02/alu.v
`timescale 1ns / 1ps

module alu(
    input signed [31:0] alu_a,
    input signed [31:0] alu_b,
    input        [4:0]  alu_op,
    output reg signed [31:0] alu_out
);

parameter A_NOP = 5'h00;  //空运算
parameter	A_ADD = 5'h01;	//符号加
parameter	A_SUB = 5'h02;	//符号减
parameter	A_AND = 5'h03;	//与
parameter	A_OR = 5'h04;	//或
parameter	A_XOR = 5'h05;	//异或
parameter	A_NOR = 5'h06;	//或非

always@(*) begin
  case (alu_op)
    A_NOP: alu_out = alu_a;
    A_ADD: alu_out = alu_a + alu_b;
    A_SUB: alu_out = alu_a - alu_b;
    A_AND: alu_out = alu_a & alu_b;
    A_OR: alu_out = alu_a | alu_b;
    A_XOR: alu_out = alu_a ^ alu_b;
    A_NOR: alu_out = ~(alu_a | alu_b);
    default: alu_out = alu_a;
  endcase
end

endmodule

lab02/regfile.v
`timescale 1ns / 1ps

module regfile(
	input 			clk,
	input 			rst_n,
	input 	[5:0] 	rAddr,
	output reg	[31:0] 	rDout,
	input 	[5:0] 	wAddr,
	input 	[31:0] 	wDin,
	input			wEna
);

reg [31:0] data [0:63];
integer i;

always@(*) begin
	if(~wEna)
		rDout = data[rAddr];
end

always@(posedge clk or negedge rst_n) begin
	if(~rst_n) begin
		data[0] <= 32'h0002;
		data[1] <= 32'h0002;
		for(i = 2; i < 64; i = i + 1)
			data[i] <= 0;	
	end
	if(wEna)
		data[wAddr] = wDin;
end

endmodule

lab02/control.v
`timescale 1ns / 1ps

module control(
	input clk,
	input rst_n,
	input [31:0] r0,
	output reg [5:0] rAddr,
	output reg [5:0] wAddr,
	output reg [31:0] a,
	output reg [31:0] b,
	output reg wEna
);

reg [2:0] num;
	 
always@(posedge clk or negedge rst_n) begin
	if(~rst_n) begin
		rAddr <= 0;
		wAddr <= 1;
		num <= 0;
		a <= 2;
	end
	else if(num == 0) begin
		wEna <= 0;
		rAddr <= rAddr;
		num <= num + 1;
	end
	else if(num == 1) begin
		a <= r0;
		num <= num + 1;
	end
	else if(num == 2) begin
		num <= num + 1;
		rAddr <= rAddr + 1;
	end
	else if(num == 3) begin
		num <= num + 1;
		b <= r0;
	end
	else if(num == 4) begin
		wEna <= 1;
		num <= 0;
		wAddr <= wAddr + 1;
	end
end

endmodule

lab02/top.v
`timescale 1ns / 1ps
`include "regfile.v"
`include "alu.v"
`include "control.v"

module top(
	input clk,
	input rst_n
);

wire [31:0] r0, a, b, c;
wire [5:0] rAddr, wAddr;
wire wEna;

control con(clk, rst_n, r0, rAddr, wAddr, a, b, wEna);
regfile r(clk, rst_n, rAddr, r0, wAddr, c, wEna);
alu alu1(a, b, 5'h1, c);

endmodule

lab02/test.v
`timescale 1ns / 1ps
`include "top.v"

module test;
	reg clk;
	reg rst_n;
	top uut (
		.clk(clk), 
		.rst_n(rst_n)
	);
	always #1 clk = ~clk;
	initial begin
		$dumpfile("test.vcd");
		$dumpvars;
		clk = 0;
		rst_n = 0;
		#2;
		rst_n = 1;
		repeat(500) @(posedge clk);
		$finish;
	end
endmodule

lab02/test.vcd
$date
	Thu Apr 12 20:44:02 2018
$end
$version
	Icarus Verilog
$end
$timescale
	1ps
$end
$scope module test $end
$var reg 1 ! clk $end
$var reg 1 " rst_n $end
$scope module uut $end
$var wire 1 ! clk $end
$var wire 1 " rst_n $end
$var wire 1 # wEna $end
$var wire 6 $ wAddr [5:0] $end
$var wire 6 % rAddr [5:0] $end
$var wire 32 & r0 [31:0] $end
$var wire 32 ' c [31:0] $end
$var wire 32 ( b [31:0] $end
$var wire 32 ) a [31:0] $end
$scope module alu1 $end
$var wire 5 * alu_op [4:0] $end
$var wire 32 + alu_b [31:0] $end
$var wire 32 , alu_a [31:0] $end
$var reg 32 - alu_out [31:0] $end
$upscope $end
$scope module con $end
$var wire 1 ! clk $end
$var wire 1 " rst_n $end
$var wire 32 . r0 [31:0] $end
$var reg 32 / a [31:0] $end
$var reg 32 0 b [31:0] $end
$var reg 3 1 num [2:0] $end
$var reg 6 2 rAddr [5:0] $end
$var reg 6 3 wAddr [5:0] $end
$var reg 1 # wEna $end
$upscope $end
$scope module r $end
$var wire 1 ! clk $end
$var wire 6 4 rAddr [5:0] $end
$var wire 1 " rst_n $end
$var wire 6 5 wAddr [5:0] $end
$var wire 32 6 wDin [31:0] $end
$var wire 1 # wEna $end
$var reg 32 7 rDout [31:0] $end
$var integer 32 8 i [31:0] $end
$upscope $end
$upscope $end
$upscope $end
$enddefinitions $end
#0
$dumpvars
b1000000 8
bx 7
bx 6
b1 5
b0 4
b1 3
b0 2
b0 1
bx 0
b10 /
bx .
bx -
b10 ,
bx +
b1 *
b10 )
bx (
bx '
bx &
b0 %
b1 $
x#
0"
0!
$end
#1000
b1000000 8
1!
#2000
0!
1"
#3000
b10 &
b10 .
b10 7
b1 1
0#
1!
#4000
0!
#5000
b10 1
1!
#6000
0!
#7000
b1 %
b1 2
b1 4
b11 1
1!
#8000
0!
#9000
b100 '
b100 -
b100 6
b10 (
b10 +
b10 0
b100 1
1!
#10000
0!
#11000
b10 $
b10 3
b10 5
b0 1
1#
1!
#12000
0!
#13000
b1 1
0#
1!
#14000
0!
#15000
b10 1
1!
#16000
0!
#17000
b100 &
b100 .
b100 7
b10 %
b10 2
b10 4
b11 1
1!
#18000
0!
#19000
b110 '
b110 -
b110 6
b100 (
b100 +
b100 0
b100 1
1!
#20000
0!
#21000
b11 $
b11 3
b11 5
b0 1
1#
1!
#22000
0!
#23000
b1 1
0#
1!
#24000
0!
#25000
b1000 '
b1000 -
b1000 6
b10 1
b100 )
b100 ,
b100 /
1!
#26000
0!
#27000
b110 &
b110 .
b110 7
b11 %
b11 2
b11 4
b11 1
1!
#28000
0!
#29000
b1010 '
b1010 -
b1010 6
b110 (
b110 +
b110 0
b100 1
1!
#30000
0!
#31000
b100 $
b100 3
b100 5
b0 1
1#
1!
#32000
0!
#33000
b1 1
0#
1!
#34000
0!
#35000
b1100 '
b1100 -
b1100 6
b10 1
b110 )
b110 ,
b110 /
1!
#36000
0!
#37000
b1010 &
b1010 .
b1010 7
b100 %
b100 2
b100 4
b11 1
1!
#38000
0!
#39000
b10000 '
b10000 -
b10000 6
b1010 (
b1010 +
b1010 0
b100 1
1!
#40000
0!
#41000
b101 $
b101 3
b101 5
b0 1
1#
1!
#42000
0!
#43000
b1 1
0#
1!
#44000
0!
#45000
b10100 '
b10100 -
b10100 6
b10 1
b1010 )
b1010 ,
b1010 /
1!
#46000
0!
#47000
b10000 &
b10000 .
b10000 7
b101 %
b101 2
b101 4
b11 1
1!
#48000
0!
#49000
b11010 '
b11010 -
b11010 6
b10000 (
b10000 +
b10000 0
b100 1
1!
#50000
0!
#51000
b110 $
b110 3
b110 5
b0 1
1#
1!
#52000
0!
#53000
b1 1
0#
1!
#54000
0!
#55000
b100000 '
b100000 -
b100000 6
b10 1
b10000 )
b10000 ,
b10000 /
1!
#56000
0!
#57000
b11010 &
b11010 .
b11010 7
b110 %
b110 2
b110 4
b11 1
1!
#58000
0!
#59000
b101010 '
b101010 -
b101010 6
b11010 (
b11010 +
b11010 0
b100 1
1!
#60000
0!
#61000
b111 $
b111 3
b111 5
b0 1
1#
1!
#62000
0!
#63000
b1 1
0#
1!
#64000
0!
#65000
b110100 '
b110100 -
b110100 6
b10 1
b11010 )
b11010 ,
b11010 /
1!
#66000
0!
#67000
b101010 &
b101010 .
b101010 7
b111 %
b111 2
b111 4
b11 1
1!
#68000
0!
#69000
b1000100 '
b1000100 -
b1000100 6
b101010 (
b101010 +
b101010 0
b100 1
1!
#70000
0!
#71000
b1000 $
b1000 3
b1000 5
b0 1
1#
1!
#72000
0!
#73000
b1 1
0#
1!
#74000
0!
#75000
b1010100 '
b1010100 -
b1010100 6
b10 1
b101010 )
b101010 ,
b101010 /
1!
#76000
0!
#77000
b1000100 &
b1000100 .
b1000100 7
b1000 %
b1000 2
b1000 4
b11 1
1!
#78000
0!
#79000
b1101110 '
b1101110 -
b1101110 6
b1000100 (
b1000100 +
b1000100 0
b100 1
1!
#80000
0!
#81000
b1001 $
b1001 3
b1001 5
b0 1
1#
1!
#82000
0!
#83000
b1 1
0#
1!
#84000
0!
#85000
b10001000 '
b10001000 -
b10001000 6
b10 1
b1000100 )
b1000100 ,
b1000100 /
1!
#86000
0!
#87000
b1101110 &
b1101110 .
b1101110 7
b1001 %
b1001 2
b1001 4
b11 1
1!
#88000
0!
#89000
b10110010 '
b10110010 -
b10110010 6
b1101110 (
b1101110 +
b1101110 0
b100 1
1!
#90000
0!
#91000
b1010 $
b1010 3
b1010 5
b0 1
1#
1!
#92000
0!
#93000
b1 1
0#
1!
#94000
0!
#95000
b11011100 '
b11011100 -
b11011100 6
b10 1
b1101110 )
b1101110 ,
b1101110 /
1!
#96000
0!
#97000
b10110010 &
b10110010 .
b10110010 7
b1010 %
b1010 2
b1010 4
b11 1
1!
#98000
0!
#99000
b100100000 '
b100100000 -
b100100000 6
b10110010 (
b10110010 +
b10110010 0
b100 1
1!
#100000
0!
#101000
b1011 $
b1011 3
b1011 5
b0 1
1#
1!
#102000
0!
#103000
b1 1
0#
1!
#104000
0!
#105000
b101100100 '
b101100100 -
b101100100 6
b10 1
b10110010 )
b10110010 ,
b10110010 /
1!
#106000
0!
#107000
b100100000 &
b100100000 .
b100100000 7
b1011 %
b1011 2
b1011 4
b11 1
1!
#108000
0!
#109000
b111010010 '
b111010010 -
b111010010 6
b100100000 (
b100100000 +
b100100000 0
b100 1
1!
#110000
0!
#111000
b1100 $
b1100 3
b1100 5
b0 1
1#
1!
#112000
0!
#113000
b1 1
0#
1!
#114000
0!
#115000
b1001000000 '
b1001000000 -
b1001000000 6
b10 1
b100100000 )
b100100000 ,
b100100000 /
1!
#116000
0!
#117000
b111010010 &
b111010010 .
b111010010 7
b1100 %
b1100 2
b1100 4
b11 1
1!
#118000
0!
#119000
b1011110010 '
b1011110010 -
b1011110010 6
b111010010 (
b111010010 +
b111010010 0
b100 1
1!
#120000
0!
#121000
b1101 $
b1101 3
b1101 5
b0 1
1#
1!
#122000
0!
#123000
b1 1
0#
1!
#124000
0!
#125000
b1110100100 '
b1110100100 -
b1110100100 6
b10 1
b111010010 )
b111010010 ,
b111010010 /
1!
#126000
0!
#127000
b1011110010 &
b1011110010 .
b1011110010 7
b1101 %
b1101 2
b1101 4
b11 1
1!
#128000
0!
#129000
b10011000100 '
b10011000100 -
b10011000100 6
b1011110010 (
b1011110010 +
b1011110010 0
b100 1
1!
#130000
0!
#131000
b1110 $
b1110 3
b1110 5
b0 1
1#
1!
#132000
0!
#133000
b1 1
0#
1!
#134000
0!
#135000
b10111100100 '
b10111100100 -
b10111100100 6
b10 1
b1011110010 )
b1011110010 ,
b1011110010 /
1!
#136000
0!
#137000
b10011000100 &
b10011000100 .
b10011000100 7
b1110 %
b1110 2
b1110 4
b11 1
1!
#138000
0!
#139000
b11110110110 '
b11110110110 -
b11110110110 6
b10011000100 (
b10011000100 +
b10011000100 0
b100 1
1!
#140000
0!
#141000
b1111 $
b1111 3
b1111 5
b0 1
1#
1!
#142000
0!
#143000
b1 1
0#
1!
#144000
0!
#145000
b100110001000 '
b100110001000 -
b100110001000 6
b10 1
b10011000100 )
b10011000100 ,
b10011000100 /
1!
#146000
0!
#147000
b11110110110 &
b11110110110 .
b11110110110 7
b1111 %
b1111 2
b1111 4
b11 1
1!
#148000
0!
#149000
b110001111010 '
b110001111010 -
b110001111010 6
b11110110110 (
b11110110110 +
b11110110110 0
b100 1
1!
#150000
0!
#151000
b10000 $
b10000 3
b10000 5
b0 1
1#
1!
#152000
0!
#153000
b1 1
0#
1!
#154000
0!
#155000
b111101101100 '
b111101101100 -
b111101101100 6
b10 1
b11110110110 )
b11110110110 ,
b11110110110 /
1!
#156000
0!
#157000
b110001111010 &
b110001111010 .
b110001111010 7
b10000 %
b10000 2
b10000 4
b11 1
1!
#158000
0!
#159000
b1010000110000 '
b1010000110000 -
b1010000110000 6
b110001111010 (
b110001111010 +
b110001111010 0
b100 1
1!
#160000
0!
#161000
b10001 $
b10001 3
b10001 5
b0 1
1#
1!
#162000
0!
#163000
b1 1
0#
1!
#164000
0!
#165000
b1100011110100 '
b1100011110100 -
b1100011110100 6
b10 1
b110001111010 )
b110001111010 ,
b110001111010 /
1!
#166000
0!
#167000
b1010000110000 &
b1010000110000 .
b1010000110000 7
b10001 %
b10001 2
b10001 4
b11 1
1!
#168000
0!
#169000
b10000010101010 '
b10000010101010 -
b10000010101010 6
b1010000110000 (
b1010000110000 +
b1010000110000 0
b100 1
1!
#170000
0!
#171000
b10010 $
b10010 3
b10010 5
b0 1
1#
1!
#172000
0!
#173000
b1 1
0#
1!
#174000
0!
#175000
b10100001100000 '
b10100001100000 -
b10100001100000 6
b10 1
b1010000110000 )
b1010000110000 ,
b1010000110000 /
1!
#176000
0!
#177000
b10000010101010 &
b10000010101010 .
b10000010101010 7
b10010 %
b10010 2
b10010 4
b11 1
1!
#178000
0!
#179000
b11010011011010 '
b11010011011010 -
b11010011011010 6
b10000010101010 (
b10000010101010 +
b10000010101010 0
b100 1
1!
#180000
0!
#181000
b10011 $
b10011 3
b10011 5
b0 1
1#
1!
#182000
0!
#183000
b1 1
0#
1!
#184000
0!
#185000
b100000101010100 '
b100000101010100 -
b100000101010100 6
b10 1
b10000010101010 )
b10000010101010 ,
b10000010101010 /
1!
#186000
0!
#187000
b11010011011010 &
b11010011011010 .
b11010011011010 7
b10011 %
b10011 2
b10011 4
b11 1
1!
#188000
0!
#189000
b101010110000100 '
b101010110000100 -
b101010110000100 6
b11010011011010 (
b11010011011010 +
b11010011011010 0
b100 1
1!
#190000
0!
#191000
b10100 $
b10100 3
b10100 5
b0 1
1#
1!
#192000
0!
#193000
b1 1
0#
1!
#194000
0!
#195000
b110100110110100 '
b110100110110100 -
b110100110110100 6
b10 1
b11010011011010 )
b11010011011010 ,
b11010011011010 /
1!
#196000
0!
#197000
b101010110000100 &
b101010110000100 .
b101010110000100 7
b10100 %
b10100 2
b10100 4
b11 1
1!
#198000
0!
#199000
b1000101001011110 '
b1000101001011110 -
b1000101001011110 6
b101010110000100 (
b101010110000100 +
b101010110000100 0
b100 1
1!
#200000
0!
#201000
b10101 $
b10101 3
b10101 5
b0 1
1#
1!
#202000
0!
#203000
b1 1
0#
1!
#204000
0!
#205000
b1010101100001000 '
b1010101100001000 -
b1010101100001000 6
b10 1
b101010110000100 )
b101010110000100 ,
b101010110000100 /
1!
#206000
0!
#207000
b1000101001011110 &
b1000101001011110 .
b1000101001011110 7
b10101 %
b10101 2
b10101 4
b11 1
1!
#208000
0!
#209000
b1101111111100010 '
b1101111111100010 -
b1101111111100010 6
b1000101001011110 (
b1000101001011110 +
b1000101001011110 0
b100 1
1!
#210000
0!
#211000
b10110 $
b10110 3
b10110 5
b0 1
1#
1!
#212000
0!
#213000
b1 1
0#
1!
#214000
0!
#215000
b10001010010111100 '
b10001010010111100 -
b10001010010111100 6
b10 1
b1000101001011110 )
b1000101001011110 ,
b1000101001011110 /
1!
#216000
0!
#217000
b1101111111100010 &
b1101111111100010 .
b1101111111100010 7
b10110 %
b10110 2
b10110 4
b11 1
1!
#218000
0!
#219000
b10110101001000000 '
b10110101001000000 -
b10110101001000000 6
b1101111111100010 (
b1101111111100010 +
b1101111111100010 0
b100 1
1!
#220000
0!
#221000
b10111 $
b10111 3
b10111 5
b0 1
1#
1!
#222000
0!
#223000
b1 1
0#
1!
#224000
0!
#225000
b11011111111000100 '
b11011111111000100 -
b11011111111000100 6
b10 1
b1101111111100010 )
b1101111111100010 ,
b1101111111100010 /
1!
#226000
0!
#227000
b10110101001000000 &
b10110101001000000 .
b10110101001000000 7
b10111 %
b10111 2
b10111 4
b11 1
1!
#228000
0!
#229000
b100100101000100010 '
b100100101000100010 -
b100100101000100010 6
b10110101001000000 (
b10110101001000000 +
b10110101001000000 0
b100 1
1!
#230000
0!
#231000
b11000 $
b11000 3
b11000 5
b0 1
1#
1!
#232000
0!
#233000
b1 1
0#
1!
#234000
0!
#235000
b101101010010000000 '
b101101010010000000 -
b101101010010000000 6
b10 1
b10110101001000000 )
b10110101001000000 ,
b10110101001000000 /
1!
#236000
0!
#237000
b100100101000100010 &
b100100101000100010 .
b100100101000100010 7
b11000 %
b11000 2
b11000 4
b11 1
1!
#238000
0!
#239000
b111011010001100010 '
b111011010001100010 -
b111011010001100010 6
b100100101000100010 (
b100100101000100010 +
b100100101000100010 0
b100 1
1!
#240000
0!
#241000
b11001 $
b11001 3
b11001 5
b0 1
1#
1!
#242000
0!
#243000
b1 1
0#
1!
#244000
0!
#245000
b1001001010001000100 '
b1001001010001000100 -
b1001001010001000100 6
b10 1
b100100101000100010 )
b100100101000100010 ,
b100100101000100010 /
1!
#246000
0!
#247000
b111011010001100010 &
b111011010001100010 .
b111011010001100010 7
b11001 %
b11001 2
b11001 4
b11 1
1!
#248000
0!
#249000
b1011111111010000100 '
b1011111111010000100 -
b1011111111010000100 6
b111011010001100010 (
b111011010001100010 +
b111011010001100010 0
b100 1
1!
#250000
0!
#251000
b11010 $
b11010 3
b11010 5
b0 1
1#
1!
#252000
0!
#253000
b1 1
0#
1!
#254000
0!
#255000
b1110110100011000100 '
b1110110100011000100 -
b1110110100011000100 6
b10 1
b111011010001100010 )
b111011010001100010 ,
b111011010001100010 /
1!
#256000
0!
#257000
b1011111111010000100 &
b1011111111010000100 .
b1011111111010000100 7
b11010 %
b11010 2
b11010 4
b11 1
1!
#258000
0!
#259000
b10011011001011100110 '
b10011011001011100110 -
b10011011001011100110 6
b1011111111010000100 (
b1011111111010000100 +
b1011111111010000100 0
b100 1
1!
#260000
0!
#261000
b11011 $
b11011 3
b11011 5
b0 1
1#
1!
#262000
0!
#263000
b1 1
0#
1!
#264000
0!
#265000
b10111111110100001000 '
b10111111110100001000 -
b10111111110100001000 6
b10 1
b1011111111010000100 )
b1011111111010000100 ,
b1011111111010000100 /
1!
#266000
0!
#267000
b10011011001011100110 &
b10011011001011100110 .
b10011011001011100110 7
b11011 %
b11011 2
b11011 4
b11 1
1!
#268000
0!
#269000
b11111011000101101010 '
b11111011000101101010 -
b11111011000101101010 6
b10011011001011100110 (
b10011011001011100110 +
b10011011001011100110 0
b100 1
1!
#270000
0!
#271000
b11100 $
b11100 3
b11100 5
b0 1
1#
1!
#272000
0!
#273000
b1 1
0#
1!
#274000
0!
#275000
b100110110010111001100 '
b100110110010111001100 -
b100110110010111001100 6
b10 1
b10011011001011100110 )
b10011011001011100110 ,
b10011011001011100110 /
1!
#276000
0!
#277000
b11111011000101101010 &
b11111011000101101010 .
b11111011000101101010 7
b11100 %
b11100 2
b11100 4
b11 1
1!
#278000
0!
#279000
b110010110010001010000 '
b110010110010001010000 -
b110010110010001010000 6
b11111011000101101010 (
b11111011000101101010 +
b11111011000101101010 0
b100 1
1!
#280000
0!
#281000
b11101 $
b11101 3
b11101 5
b0 1
1#
1!
#282000
0!
#283000
b1 1
0#
1!
#284000
0!
#285000
b111110110001011010100 '
b111110110001011010100 -
b111110110001011010100 6
b10 1
b11111011000101101010 )
b11111011000101101010 ,
b11111011000101101010 /
1!
#286000
0!
#287000
b110010110010001010000 &
b110010110010001010000 .
b110010110010001010000 7
b11101 %
b11101 2
b11101 4
b11 1
1!
#288000
0!
#289000
b1010010001010110111010 '
b1010010001010110111010 -
b1010010001010110111010 6
b110010110010001010000 (
b110010110010001010000 +
b110010110010001010000 0
b100 1
1!
#290000
0!
#291000
b11110 $
b11110 3
b11110 5
b0 1
1#
1!
#292000
0!
#293000
b1 1
0#
1!
#294000
0!
#295000
b1100101100100010100000 '
b1100101100100010100000 -
b1100101100100010100000 6
b10 1
b110010110010001010000 )
b110010110010001010000 ,
b110010110010001010000 /
1!
#296000
0!
#297000
b1010010001010110111010 &
b1010010001010110111010 .
b1010010001010110111010 7
b11110 %
b11110 2
b11110 4
b11 1
1!
#298000
0!
#299000
b10000100111101000001010 '
b10000100111101000001010 -
b10000100111101000001010 6
b1010010001010110111010 (
b1010010001010110111010 +
b1010010001010110111010 0
b100 1
1!
#300000
0!
#301000
b11111 $
b11111 3
b11111 5
b0 1
1#
1!
#302000
0!
#303000
b1 1
0#
1!
#304000
0!
#305000
b10100100010101101110100 '
b10100100010101101110100 -
b10100100010101101110100 6
b10 1
b1010010001010110111010 )
b1010010001010110111010 ,
b1010010001010110111010 /
1!
#306000
0!
#307000
b10000100111101000001010 &
b10000100111101000001010 .
b10000100111101000001010 7
b11111 %
b11111 2
b11111 4
b11 1
1!
#308000
0!
#309000
b11010111000111111000100 '
b11010111000111111000100 -
b11010111000111111000100 6
b10000100111101000001010 (
b10000100111101000001010 +
b10000100111101000001010 0
b100 1
1!
#310000
0!
#311000
b100000 $
b100000 3
b100000 5
b0 1
1#
1!
#312000
0!
#313000
b1 1
0#
1!
#314000
0!
#315000
b100001001111010000010100 '
b100001001111010000010100 -
b100001001111010000010100 6
b10 1
b10000100111101000001010 )
b10000100111101000001010 ,
b10000100111101000001010 /
1!
#316000
0!
#317000
b11010111000111111000100 &
b11010111000111111000100 .
b11010111000111111000100 7
b100000 %
b100000 2
b100000 4
b11 1
1!
#318000
0!
#319000
b101011100000100111001110 '
b101011100000100111001110 -
b101011100000100111001110 6
b11010111000111111000100 (
b11010111000111111000100 +
b11010111000111111000100 0
b100 1
1!
#320000
0!
#321000
b100001 $
b100001 3
b100001 5
b0 1
1#
1!
#322000
0!
#323000
b1 1
0#
1!
#324000
0!
#325000
b110101110001111110001000 '
b110101110001111110001000 -
b110101110001111110001000 6
b10 1
b11010111000111111000100 )
b11010111000111111000100 ,
b11010111000111111000100 /
1!
#326000
0!
#327000
b101011100000100111001110 &
b101011100000100111001110 .
b101011100000100111001110 7
b100001 %
b100001 2
b100001 4
b11 1
1!
#328000
0!
#329000
b1000110011001100110010010 '
b1000110011001100110010010 -
b1000110011001100110010010 6
b101011100000100111001110 (
b101011100000100111001110 +
b101011100000100111001110 0
b100 1
1!
#330000
0!
#331000
b100010 $
b100010 3
b100010 5
b0 1
1#
1!
#332000
0!
#333000
b1 1
0#
1!
#334000
0!
#335000
b1010111000001001110011100 '
b1010111000001001110011100 -
b1010111000001001110011100 6
b10 1
b101011100000100111001110 )
b101011100000100111001110 ,
b101011100000100111001110 /
1!
#336000
0!
#337000
b1000110011001100110010010 &
b1000110011001100110010010 .
b1000110011001100110010010 7
b100010 %
b100010 2
b100010 4
b11 1
1!
#338000
0!
#339000
b1110001111010001101100000 '
b1110001111010001101100000 -
b1110001111010001101100000 6
b1000110011001100110010010 (
b1000110011001100110010010 +
b1000110011001100110010010 0
b100 1
1!
#340000
0!
#341000
b100011 $
b100011 3
b100011 5
b0 1
1#
1!
#342000
0!
#343000
b1 1
0#
1!
#344000
0!
#345000
b10001100110011001100100100 '
b10001100110011001100100100 -
b10001100110011001100100100 6
b10 1
b1000110011001100110010010 )
b1000110011001100110010010 ,
b1000110011001100110010010 /
1!
#346000
0!
#347000
b1110001111010001101100000 &
b1110001111010001101100000 .
b1110001111010001101100000 7
b100011 %
b100011 2
b100011 4
b11 1
1!
#348000
0!
#349000
b10111000010011110011110010 '
b10111000010011110011110010 -
b10111000010011110011110010 6
b1110001111010001101100000 (
b1110001111010001101100000 +
b1110001111010001101100000 0
b100 1
1!
#350000
0!
#351000
b100100 $
b100100 3
b100100 5
b0 1
1#
1!
#352000
0!
#353000
b1 1
0#
1!
#354000
0!
#355000
b11100011110100011011000000 '
b11100011110100011011000000 -
b11100011110100011011000000 6
b10 1
b1110001111010001101100000 )
b1110001111010001101100000 ,
b1110001111010001101100000 /
1!
#356000
0!
#357000
b10111000010011110011110010 &
b10111000010011110011110010 .
b10111000010011110011110010 7
b100100 %
b100100 2
b100100 4
b11 1
1!
#358000
0!
#359000
b100101010001110000001010010 '
b100101010001110000001010010 -
b100101010001110000001010010 6
b10111000010011110011110010 (
b10111000010011110011110010 +
b10111000010011110011110010 0
b100 1
1!
#360000
0!
#361000
b100101 $
b100101 3
b100101 5
b0 1
1#
1!
#362000
0!
#363000
b1 1
0#
1!
#364000
0!
#365000
b101110000100111100111100100 '
b101110000100111100111100100 -
b101110000100111100111100100 6
b10 1
b10111000010011110011110010 )
b10111000010011110011110010 ,
b10111000010011110011110010 /
1!
#366000
0!
#367000
b100101010001110000001010010 &
b100101010001110000001010010 .
b100101010001110000001010010 7
b100101 %
b100101 2
b100101 4
b11 1
1!
#368000
0!
#369000
b111100010100001110101000100 '
b111100010100001110101000100 -
b111100010100001110101000100 6
b100101010001110000001010010 (
b100101010001110000001010010 +
b100101010001110000001010010 0
b100 1
1!
#370000
0!
#371000
b100110 $
b100110 3
b100110 5
b0 1
1#
1!
#372000
0!
#373000
b1 1
0#
1!
#374000
0!
#375000
b1001010100011100000010100100 '
b1001010100011100000010100100 -
b1001010100011100000010100100 6
b10 1
b100101010001110000001010010 )
b100101010001110000001010010 ,
b100101010001110000001010010 /
1!
#376000
0!
#377000
b111100010100001110101000100 &
b111100010100001110101000100 .
b111100010100001110101000100 7
b100110 %
b100110 2
b100110 4
b11 1
1!
#378000
0!
#379000
b1100001100101111110110010110 '
b1100001100101111110110010110 -
b1100001100101111110110010110 6
b111100010100001110101000100 (
b111100010100001110101000100 +
b111100010100001110101000100 0
b100 1
1!
#380000
0!
#381000
b100111 $
b100111 3
b100111 5
b0 1
1#
1!
#382000
0!
#383000
b1 1
0#
1!
#384000
0!
#385000
b1111000101000011101010001000 '
b1111000101000011101010001000 -
b1111000101000011101010001000 6
b10 1
b111100010100001110101000100 )
b111100010100001110101000100 ,
b111100010100001110101000100 /
1!
#386000
0!
#387000
b1100001100101111110110010110 &
b1100001100101111110110010110 .
b1100001100101111110110010110 7
b100111 %
b100111 2
b100111 4
b11 1
1!
#388000
0!
#389000
b10011101111010001101011011010 '
b10011101111010001101011011010 -
b10011101111010001101011011010 6
b1100001100101111110110010110 (
b1100001100101111110110010110 +
b1100001100101111110110010110 0
b100 1
1!
#390000
0!
#391000
b101000 $
b101000 3
b101000 5
b0 1
1#
1!
#392000
0!
#393000
b1 1
0#
1!
#394000
0!
#395000
b11000011001011111101100101100 '
b11000011001011111101100101100 -
b11000011001011111101100101100 6
b10 1
b1100001100101111110110010110 )
b1100001100101111110110010110 ,
b1100001100101111110110010110 /
1!
#396000
0!
#397000
b10011101111010001101011011010 &
b10011101111010001101011011010 .
b10011101111010001101011011010 7
b101000 %
b101000 2
b101000 4
b11 1
1!
#398000
0!
#399000
b11111111100000001100001110000 '
b11111111100000001100001110000 -
b11111111100000001100001110000 6
b10011101111010001101011011010 (
b10011101111010001101011011010 +
b10011101111010001101011011010 0
b100 1
1!
#400000
0!
#401000
b101001 $
b101001 3
b101001 5
b0 1
1#
1!
#402000
0!
#403000
b1 1
0#
1!
#404000
0!
#405000
b100111011110100011010110110100 '
b100111011110100011010110110100 -
b100111011110100011010110110100 6
b10 1
b10011101111010001101011011010 )
b10011101111010001101011011010 ,
b10011101111010001101011011010 /
1!
#406000
0!
#407000
b11111111100000001100001110000 &
b11111111100000001100001110000 .
b11111111100000001100001110000 7
b101001 %
b101001 2
b101001 4
b11 1
1!
#408000
0!
#409000
b110011101011010011001101001010 '
b110011101011010011001101001010 -
b110011101011010011001101001010 6
b11111111100000001100001110000 (
b11111111100000001100001110000 +
b11111111100000001100001110000 0
b100 1
1!
#410000
0!
#411000
b101010 $
b101010 3
b101010 5
b0 1
1#
1!
#412000
0!
#413000
b1 1
0#
1!
#414000
0!
#415000
b111111111000000011000011100000 '
b111111111000000011000011100000 -
b111111111000000011000011100000 6
b10 1
b11111111100000001100001110000 )
b11111111100000001100001110000 ,
b11111111100000001100001110000 /
1!
#416000
0!
#417000
b110011101011010011001101001010 &
b110011101011010011001101001010 .
b110011101011010011001101001010 7
b101010 %
b101010 2
b101010 4
b11 1
1!
#418000
0!
#419000
b1010011100111010100101110111010 '
b1010011100111010100101110111010 -
b1010011100111010100101110111010 6
b110011101011010011001101001010 (
b110011101011010011001101001010 +
b110011101011010011001101001010 0
b100 1
1!
#420000
0!
#421000
b101011 $
b101011 3
b101011 5
b0 1
1#
1!
#422000
0!
#423000
b1 1
0#
1!
#424000
0!
#425000
b1100111010110100110011010010100 '
b1100111010110100110011010010100 -
b1100111010110100110011010010100 6
b10 1
b110011101011010011001101001010 )
b110011101011010011001101001010 ,
b110011101011010011001101001010 /
1!
#426000
0!
#427000
b1010011100111010100101110111010 &
b1010011100111010100101110111010 .
b1010011100111010100101110111010 7
b101011 %
b101011 2
b101011 4
b11 1
1!
#428000
0!
#429000
b10000111010010100111111100000100 '
b10000111010010100111111100000100 -
b10000111010010100111111100000100 6
b1010011100111010100101110111010 (
b1010011100111010100101110111010 +
b1010011100111010100101110111010 0
b100 1
1!
#430000
0!
#431000
b101100 $
b101100 3
b101100 5
b0 1
1#
1!
#432000
0!
#433000
b1 1
0#
1!
#434000
0!
#435000
b10100111001110101001011101110100 '
b10100111001110101001011101110100 -
b10100111001110101001011101110100 6
b10 1
b1010011100111010100101110111010 )
b1010011100111010100101110111010 ,
b1010011100111010100101110111010 /
1!
#436000
0!
#437000
b10000111010010100111111100000100 &
b10000111010010100111111100000100 .
b10000111010010100111111100000100 7
b101100 %
b101100 2
b101100 4
b11 1
1!
#438000
0!
#439000
b11011010111001111100101010111110 '
b11011010111001111100101010111110 -
b11011010111001111100101010111110 6
b10000111010010100111111100000100 (
b10000111010010100111111100000100 +
b10000111010010100111111100000100 0
b100 1
1!
#440000
0!
#441000
b101101 $
b101101 3
b101101 5
b0 1
1#
1!
#442000
0!
#443000
b1 1
0#
1!
#444000
0!
