lab01/alu.v
`timescale 1ns / 1ps

module alu(
    input signed [31:0] alu_a,
    input signed [31:0] alu_b,
    input        [4:0]  alu_op,
    output reg signed  [31:0] alu_out
);

parameter A_NOP = 5'h00;  //空运算
parameter	A_ADD = 5'h01;	//符号加
parameter	A_SUB = 5'h02;	//符号减
parameter	A_AND = 5'h03;	//与
parameter	A_OR = 5'h04;	  //或
parameter	A_XOR = 5'h05;	//异或
parameter	A_NOR = 5'h06;	//或非

always@(*) begin
  case (alu_op)
    A_NOP: alu_out = alu_a;
    A_ADD: alu_out = alu_a + alu_b;
    A_SUB: alu_out = alu_a - alu_b;
    A_AND: alu_out = alu_a & alu_b;
    A_OR: alu_out = alu_a | alu_b;
    A_XOR: alu_out = alu_a ^ alu_b;
    A_NOR: alu_out = ~(alu_a | alu_b);
    default: alu_out = alu_a;
  endcase
end

endmodule

lab01/test_alu.v
`timescale 1ns / 1ps
`include "alu.v"

module test;
    reg [31:0] a;
    reg [31:0] b;
    reg [4:0]  op;
    wire [31:0] out;
    alu uut (
        .alu_a(a),
        .alu_b(b),
        .alu_op(op),
        .alu_out(out)
    );

    initial begin
		$dumpfile("test_alu.vcd");
		$dumpvars;
        op = 0;
        a = 0;
        b = 0;
        #100;
        op = 0;
        a = 3;
        b = 2;
		#100;
        op = 1;
        a = 10;
        b = 7;
        #100;
        op = 2;
        a = 5;
        b = 8;
        #100;
        op = 3;
        a = 11;
        b = 19;
        #100;
        op = 4;
        a = 18;
        b = 23;
        #100;
        op = 5;
        a = 24;
        b = 16;
        #100;
        op = 6;
        a = 13;
        b = 31;
        #100;
		$finish;

    end
endmodule

lab01/test_alu.vcd
$date
	Thu Apr 12 18:16:53 2018
$end
$version
	Icarus Verilog
$end
$timescale
	1ps
$end
$scope module test $end
$var wire 32 ! out [31:0] $end
$var reg 32 " a [31:0] $end
$var reg 32 # b [31:0] $end
$var reg 5 $ op [4:0] $end
$scope module uut $end
$var wire 32 % alu_a [31:0] $end
$var wire 32 & alu_b [31:0] $end
$var wire 5 ' alu_op [4:0] $end
$var reg 32 ( alu_out [31:0] $end
$upscope $end
$upscope $end
$enddefinitions $end
#0
$dumpvars
b0 (
b0 '
b0 &
b0 %
b0 $
b0 #
b0 "
b0 !
$end
#100000
b11 !
b11 (
b10 #
b10 &
b11 "
b11 %
#200000
b10001 !
b10001 (
b111 #
b111 &
b1010 "
b1010 %
b1 $
b1 '
#300000
b11111111111111111111111111111101 !
b11111111111111111111111111111101 (
b1000 #
b1000 &
b101 "
b101 %
b10 $
b10 '
#400000
b11 !
b11 (
b10011 #
b10011 &
b1011 "
b1011 %
b11 $
b11 '
#500000
b10111 !
b10111 (
b10111 #
b10111 &
b10010 "
b10010 %
b100 $
b100 '
#600000
b1000 !
b1000 (
b10000 #
b10000 &
b11000 "
b11000 %
b101 $
b101 '
#700000
b11111111111111111111111111100000 !
b11111111111111111111111111100000 (
b11111 #
b11111 &
b1101 "
b1101 %
b110 $
b110 '
